coldatoms/__init__.py
coldatoms/bend_kick.py
coldatoms/coulomb.py
coldatoms/particles.py
coldatoms/penning_trap.py
coldatoms/radiation_pressure.py
coldatoms/version.py
coldatoms-0.1.11.dist-info/DESCRIPTION.rst
coldatoms-0.1.11.dist-info/METADATA
coldatoms-0.1.11.dist-info/RECORD
coldatoms-0.1.11.dist-info/WHEEL
coldatoms-0.1.11.dist-info/metadata.json
coldatoms-0.1.11.dist-info/top_level.txt
coldatoms_lib/__init__.py
coldatoms_lib/coldatoms_lib.pyd
