Metadata-Version: 2.0
Name: coldatoms
Version: 0.1.11
Summary: Collection of python tools for cold atoms simulations
Home-page: https://github.com/d-meiser/cold-atoms
Author: Dominic Meiser
Author-email: dmeiser79@gmail.com
License: GPLv3
Platform: UNKNOWN
Classifier: Development Status :: 3 - Alpha
Classifier: Intended Audience :: Education
Classifier: Intended Audience :: Science/Research
Classifier: License :: OSI Approved :: GNU General Public License v3 (GPLv3)
Classifier: Programming Language :: Python :: 2
Classifier: Programming Language :: Python :: 2.7
Classifier: Programming Language :: Python :: 3
Classifier: Programming Language :: Python :: 3.4
Classifier: Topic :: Scientific/Engineering :: Physics
Requires-Dist: cython
Requires-Dist: numpy
